<?xml version="1.0"?>
<MusicSheet xmlns:xsi="http://www.w3.org/2001/XMLSchema-instance" xmlns:xsd="http://www.w3.org/2001/XMLSchema">
  <Title>Success Beep 1</Title>
  <Note>
    <Tone>OTHER</Tone>
    <Frequency>0</Frequency>
    <Duration>100</Duration>
  </Note>
  <Note>
    <Tone>OTHER</Tone>
    <Frequency>392</Frequency>
    <Duration>50</Duration>
  </Note>
  <Note>
    <Tone>OTHER</Tone>
    <Frequency>440</Frequency>
    <Duration>50</Duration>
  </Note>
  <Note>
    <Tone>A4Sharp</Tone>
    <Frequency>466</Frequency>
    <Duration>100</Duration>
  </Note>
  <Note>
    <Tone>REST</Tone>
    <Frequency>0</Frequency>
    <Duration>100</Duration>
  </Note>
  <Note>
    <Tone>OTHER</Tone>
    <Frequency>349</Frequency>
    <Duration>50</Duration>
  </Note>
  <Note>
    <Tone>REST</Tone>
    <Frequency>0</Frequency>
    <Duration>50</Duration>
  </Note>
  <Note>
    <Tone>REST</Tone>
    <Frequency>0</Frequency>
    <Duration>100</Duration>
  </Note>
  <Note>
    <Tone>A4Sharp</Tone>
    <Frequency>466</Frequency>
    <Duration>100</Duration>
  </Note>
</MusicSheet>